Calendar/__init__.py
Calendar/calendar_functions.py
Calendar/main.py
py_calendar_entry_management_functions-0.1.1.dist-info/METADATA
py_calendar_entry_management_functions-0.1.1.dist-info/WHEEL
py_calendar_entry_management_functions-0.1.1.dist-info/top_level.txt
py_calendar_entry_management_functions-0.1.1.dist-info/RECORD
