Metadata-Version: 2.1
Name: py-calendar-entry-management-functions
Version: 0.1.1
Summary: A package to store and access calendar entries in a json file .
Home-page: UNKNOWN
Author: Leon
Author-email: leonz99@web.de
License: UNKNOWN
Platform: UNKNOWN
Classifier: Programming Language :: Python :: 3
Classifier: License :: OSI Approved :: MIT License
Classifier: Operating System :: OS Independent
Requires-Python: >=3.6
Requires-Dist: datetime
